LICENSE.md
MANIFEST.in
README.md
setup.py
admin_coreui/__init__.py
admin_coreui/admin.py
admin_coreui/apps.py
admin_coreui/forms.py
admin_coreui/models.py
admin_coreui/tests.py
admin_coreui/urls.py
admin_coreui/utils.py
admin_coreui/views.py
admin_coreui/migrations/__init__.py
admin_coreui/static/assets/package-lock.json
admin_coreui/static/assets/package.json
admin_coreui/static/assets/brand/coreui.svg
admin_coreui/static/assets/css/forms.css
admin_coreui/static/assets/css/widgets.css
admin_coreui/static/assets/favicon/android-icon-144x144.png
admin_coreui/static/assets/favicon/android-icon-192x192.png
admin_coreui/static/assets/favicon/android-icon-36x36.png
admin_coreui/static/assets/favicon/android-icon-48x48.png
admin_coreui/static/assets/favicon/android-icon-72x72.png
admin_coreui/static/assets/favicon/android-icon-96x96.png
admin_coreui/static/assets/favicon/apple-icon-114x114.png
admin_coreui/static/assets/favicon/apple-icon-120x120.png
admin_coreui/static/assets/favicon/apple-icon-144x144.png
admin_coreui/static/assets/favicon/apple-icon-152x152.png
admin_coreui/static/assets/favicon/apple-icon-180x180.png
admin_coreui/static/assets/favicon/apple-icon-57x57.png
admin_coreui/static/assets/favicon/apple-icon-60x60.png
admin_coreui/static/assets/favicon/apple-icon-72x72.png
admin_coreui/static/assets/favicon/apple-icon-76x76.png
admin_coreui/static/assets/favicon/apple-icon-precomposed.png
admin_coreui/static/assets/favicon/apple-icon.png
admin_coreui/static/assets/favicon/browserconfig.xml
admin_coreui/static/assets/favicon/favicon-16x16.png
admin_coreui/static/assets/favicon/favicon-32x32.png
admin_coreui/static/assets/favicon/favicon-96x96.png
admin_coreui/static/assets/favicon/favicon.ico
admin_coreui/static/assets/favicon/manifest.json
admin_coreui/static/assets/favicon/ms-icon-144x144.png
admin_coreui/static/assets/favicon/ms-icon-150x150.png
admin_coreui/static/assets/favicon/ms-icon-310x310.png
admin_coreui/static/assets/favicon/ms-icon-70x70.png
django_admin_coreui.egg-info/PKG-INFO
django_admin_coreui.egg-info/SOURCES.txt
django_admin_coreui.egg-info/dependency_links.txt
django_admin_coreui.egg-info/not-zip-safe
django_admin_coreui.egg-info/top_level.txt